{"dur":31.275,"words":[{"t":0.1,"c":0},{"t":0.475,"c":4},{"t":0.688,"c":7},{"t":1.363,"c":16},{"t":2.587,"c":22},{"t":2.862,"c":25},{"t":3.075,"c":28},{"t":3.325,"c":31},{"t":3.888,"c":41},{"t":4.225,"c":46},{"t":4.963,"c":53},{"t":5.775,"c":62},{"t":7.05,"c":69},{"t":7.287,"c":72},{"t":7.787,"c":80},{"t":8.563,"c":85},{"t":8.975,"c":91},{"t":9.338,"c":98},{"t":9.95,"c":104},{"t":10.6,"c":111},{"t":11.037,"c":118},{"t":11.425,"c":123},{"t":11.65,"c":126},{"t":12.262,"c":133},{"t":12.575,"c":137},{"t":13.012,"c":144},{"t":13.637,"c":149},{"t":13.938,"c":152},{"t":14.25,"c":157},{"t":14.625,"c":161},{"t":15.175,"c":167},{"t":15.738,"c":176},{"t":16.137,"c":181},{"t":17.538,"c":188},{"t":18.438,"c":194},{"t":19.288,"c":202},{"t":19.6,"c":206},{"t":19.813,"c":209},{"t":20.363,"c":215},{"t":21.038,"c":222},{"t":21.462,"c":229},{"t":21.925,"c":234},{"t":22.137,"c":237},{"t":22.563,"c":243},{"t":23.188,"c":250},{"t":23.637,"c":259},{"t":24.45,"c":270},{"t":25,"c":276},{"t":25.212,"c":279},{"t":26.087,"c":290},{"t":26.425,"c":296},{"t":27.288,"c":302},{"t":27.775,"c":309},{"t":28.188,"c":315},{"t":28.5,"c":320},{"t":28.813,"c":325},{"t":29.275,"c":330},{"t":29.938,"c":338},{"t":30.45,"c":343},{"t":30.9,"c":349}]}