{"dur":30.275,"words":[{"t":0.1,"c":0},{"t":0.425,"c":5},{"t":1.025,"c":16},{"t":1.538,"c":26},{"t":1.75,"c":30},{"t":2.038,"c":35},{"t":2.712,"c":42},{"t":3.087,"c":46},{"t":3.725,"c":53},{"t":5.45,"c":65},{"t":6.1,"c":73},{"t":6.787,"c":84},{"t":7.25,"c":91},{"t":7.612,"c":96},{"t":8.25,"c":105},{"t":9.238,"c":118},{"t":9.675,"c":123},{"t":10.325,"c":134},{"t":10.8,"c":141},{"t":11.225,"c":149},{"t":12.162,"c":163},{"t":12.725,"c":174},{"t":13.313,"c":184},{"t":14.162,"c":195},{"t":16.113,"c":214},{"t":16.4,"c":219},{"t":17.075,"c":230},{"t":17.613,"c":237},{"t":18.075,"c":247},{"t":19,"c":260},{"t":19.5,"c":268},{"t":19.938,"c":274},{"t":20.85,"c":290},{"t":21.688,"c":302},{"t":22.325,"c":310},{"t":22.837,"c":317},{"t":24.288,"c":327},{"t":25.012,"c":334},{"t":25.8,"c":345},{"t":26.163,"c":349},{"t":26.913,"c":360},{"t":27.275,"c":377},{"t":27.675,"c":394},{"t":28.012,"c":398},{"t":28.55,"c":408},{"t":29.225,"c":418}]}