{"dur":23.175,"words":[{"t":0.1,"c":0},{"t":0.725,"c":6},{"t":1.163,"c":10},{"t":2.388,"c":15},{"t":2.813,"c":22},{"t":3.612,"c":32},{"t":3.888,"c":35},{"t":4.287,"c":41},{"t":4.675,"c":47},{"t":5.15,"c":52},{"t":5.662,"c":59},{"t":6.037,"c":68},{"t":6.5,"c":73},{"t":6.925,"c":79},{"t":7.162,"c":83},{"t":7.6,"c":87},{"t":8.113,"c":93},{"t":8.65,"c":99},{"t":9.4,"c":106},{"t":9.7,"c":110},{"t":10.175,"c":116},{"t":10.838,"c":127},{"t":11.15,"c":131},{"t":12.037,"c":142},{"t":12.387,"c":146},{"t":13.713,"c":152},{"t":14.063,"c":155},{"t":14.325,"c":158},{"t":14.787,"c":163},{"t":15.113,"c":169},{"t":15.8,"c":174},{"t":16.038,"c":177},{"t":16.25,"c":180},{"t":16.863,"c":187},{"t":17.6,"c":196},{"t":18.238,"c":206},{"t":18.863,"c":214},{"t":19.212,"c":218},{"t":19.913,"c":225},{"t":20.837,"c":239},{"t":21.363,"c":247},{"t":22.163,"c":254}]}