{"dur":31.25,"words":[{"t":0.1,"c":0},{"t":0.35,"c":3},{"t":0.588,"c":6},{"t":1.075,"c":14},{"t":1.337,"c":17},{"t":1.587,"c":20},{"t":2.025,"c":26},{"t":2.413,"c":31},{"t":2.737,"c":36},{"t":4.237,"c":44},{"t":4.625,"c":49},{"t":5.112,"c":59},{"t":5.287,"c":62},{"t":5.938,"c":67},{"t":6.438,"c":74},{"t":6.912,"c":82},{"t":7.3,"c":89},{"t":7.513,"c":92},{"t":7.975,"c":100},{"t":8.65,"c":108},{"t":9.113,"c":111},{"t":9.338,"c":114},{"t":9.675,"c":119},{"t":10.063,"c":127},{"t":10.238,"c":130},{"t":10.825,"c":138},{"t":11.225,"c":143},{"t":11.6,"c":149},{"t":12.162,"c":158},{"t":12.512,"c":165},{"t":13.162,"c":173},{"t":14.7,"c":182},{"t":14.963,"c":185},{"t":15.425,"c":193},{"t":15.6,"c":196},{"t":16.45,"c":206},{"t":16.837,"c":211},{"t":17.238,"c":219},{"t":17.587,"c":224},{"t":18.1,"c":229},{"t":18.512,"c":237},{"t":18.975,"c":245},{"t":19.363,"c":252},{"t":19.762,"c":258},{"t":20.25,"c":264},{"t":20.775,"c":269},{"t":21.025,"c":272},{"t":21.337,"c":279},{"t":21.788,"c":285},{"t":22.45,"c":293},{"t":22.637,"c":296},{"t":23.025,"c":302},{"t":23.5,"c":310},{"t":23.975,"c":317},{"t":24.2,"c":320},{"t":24.413,"c":324},{"t":25.012,"c":332},{"t":25.75,"c":342},{"t":26.325,"c":350},{"t":26.512,"c":353},{"t":26.813,"c":358},{"t":27.363,"c":366},{"t":28.863,"c":373},{"t":29.125,"c":376},{"t":29.6,"c":381},{"t":29.825,"c":384},{"t":30.125,"c":387},{"t":30.512,"c":392}]}