{"dur":28.863,"words":[{"t":0.1,"c":0},{"t":1.175,"c":11},{"t":2.925,"c":24},{"t":3.563,"c":31},{"t":4.138,"c":39},{"t":4.6,"c":48},{"t":5.787,"c":63},{"t":6.325,"c":71},{"t":7.05,"c":80},{"t":7.737,"c":94},{"t":8.425,"c":102},{"t":9.063,"c":112},{"t":9.6,"c":120},{"t":10.137,"c":129},{"t":10.713,"c":139},{"t":12.275,"c":151},{"t":13.063,"c":162},{"t":14.125,"c":177},{"t":15.675,"c":188},{"t":16.587,"c":200},{"t":16.975,"c":206},{"t":17.775,"c":219},{"t":18.663,"c":232},{"t":19.762,"c":248},{"t":21.012,"c":267},{"t":21.375,"c":274},{"t":21.725,"c":279},{"t":23.175,"c":288},{"t":23.563,"c":294},{"t":23.95,"c":299},{"t":24.387,"c":304},{"t":24.863,"c":312},{"t":25.375,"c":320},{"t":25.938,"c":331},{"t":27.175,"c":344},{"t":27.575,"c":351},{"t":28.05,"c":360}]}