{"dur":27.762,"words":[{"t":0.1,"c":0},{"t":0.625,"c":5},{"t":1.137,"c":11},{"t":1.75,"c":17},{"t":2.15,"c":23},{"t":2.388,"c":26},{"t":2.638,"c":29},{"t":2.95,"c":32},{"t":3.25,"c":37},{"t":3.638,"c":43},{"t":4.188,"c":50},{"t":4.588,"c":55},{"t":6.125,"c":66},{"t":6.537,"c":73},{"t":7,"c":78},{"t":7.362,"c":82},{"t":7.8,"c":87},{"t":8.113,"c":92},{"t":8.988,"c":98},{"t":9.4,"c":104},{"t":9.875,"c":111},{"t":10.25,"c":117},{"t":10.637,"c":123},{"t":11.325,"c":130},{"t":12.1,"c":135},{"t":12.588,"c":141},{"t":12.912,"c":146},{"t":13.363,"c":151},{"t":14.113,"c":160},{"t":14.762,"c":169},{"t":15.363,"c":177},{"t":15.887,"c":184},{"t":16.25,"c":189},{"t":16.788,"c":195},{"t":17.212,"c":199},{"t":17.725,"c":208},{"t":18.175,"c":213},{"t":18.575,"c":219},{"t":19.3,"c":228},{"t":19.65,"c":234},{"t":20.962,"c":241},{"t":21.438,"c":247},{"t":21.688,"c":250},{"t":21.938,"c":253},{"t":22.238,"c":256},{"t":22.837,"c":263},{"t":23.275,"c":267},{"t":23.738,"c":272},{"t":24.025,"c":277},{"t":24.875,"c":282},{"t":25.413,"c":291},{"t":25.813,"c":298},{"t":26.35,"c":305},{"t":27.125,"c":317},{"t":27.4,"c":322}]}