{"dur":26.3,"words":[{"t":0.1,"c":0},{"t":0.588,"c":6},{"t":1.05,"c":13},{"t":1.438,"c":19},{"t":2.075,"c":25},{"t":2.913,"c":36},{"t":3.25,"c":41},{"t":3.8,"c":48},{"t":5.05,"c":54},{"t":5.575,"c":63},{"t":6.188,"c":69},{"t":6.563,"c":76},{"t":7.037,"c":83},{"t":7.75,"c":92},{"t":8.1,"c":95},{"t":8.475,"c":101},{"t":8.988,"c":107},{"t":9.412,"c":111},{"t":9.675,"c":114},{"t":10.2,"c":122},{"t":10.575,"c":126},{"t":12.012,"c":134},{"t":12.588,"c":140},{"t":13.3,"c":146},{"t":13.662,"c":150},{"t":14.325,"c":159},{"t":14.725,"c":164},{"t":15.037,"c":169},{"t":15.3,"c":171},{"t":15.512,"c":174},{"t":16.762,"c":179},{"t":17.238,"c":185},{"t":17.4,"c":188},{"t":17.775,"c":192},{"t":18.012,"c":196},{"t":18.875,"c":202},{"t":19.25,"c":208},{"t":19.563,"c":212},{"t":20.137,"c":219},{"t":20.663,"c":225},{"t":21.837,"c":229},{"t":22.375,"c":236},{"t":22.85,"c":243},{"t":23.075,"c":246},{"t":23.6,"c":253},{"t":24.175,"c":259},{"t":24.762,"c":267},{"t":25.05,"c":274},{"t":25.55,"c":280},{"t":25.9,"c":285}]}