{"dur":29.913,"words":[{"t":0.1,"c":0},{"t":1.175,"c":12},{"t":1.637,"c":19},{"t":2.05,"c":25},{"t":3.337,"c":31},{"t":3.95,"c":39},{"t":4.662,"c":45},{"t":5.013,"c":49},{"t":5.588,"c":55},{"t":5.912,"c":58},{"t":6.2,"c":62},{"t":6.7,"c":70},{"t":7.7,"c":81},{"t":8.137,"c":87},{"t":8.563,"c":91},{"t":9.15,"c":97},{"t":9.488,"c":101},{"t":10.1,"c":109},{"t":10.287,"c":111},{"t":10.512,"c":114},{"t":10.775,"c":117},{"t":11.287,"c":124},{"t":11.7,"c":131},{"t":11.988,"c":136},{"t":12.762,"c":142},{"t":13.225,"c":147},{"t":13.6,"c":150},{"t":14.188,"c":156},{"t":14.463,"c":160},{"t":14.813,"c":165},{"t":15.4,"c":174},{"t":15.887,"c":181},{"t":16.313,"c":187},{"t":17.087,"c":193},{"t":17.4,"c":197},{"t":18.087,"c":205},{"t":18.663,"c":211},{"t":18.913,"c":214},{"t":19.337,"c":219},{"t":20.575,"c":224},{"t":20.962,"c":228},{"t":21.45,"c":235},{"t":21.988,"c":243},{"t":22.262,"c":246},{"t":22.613,"c":253},{"t":23.45,"c":259},{"t":23.688,"c":262},{"t":23.875,"c":265},{"t":24.313,"c":270},{"t":25,"c":276},{"t":25.325,"c":280},{"t":25.887,"c":286},{"t":26.15,"c":289},{"t":26.488,"c":292},{"t":26.762,"c":296},{"t":28.075,"c":303},{"t":28.663,"c":310},{"t":29.538,"c":321}]}