{"dur":26.012,"words":[{"t":0.1,"c":0},{"t":0.713,"c":10},{"t":1.188,"c":18},{"t":1.913,"c":30},{"t":2.825,"c":47},{"t":3.65,"c":54},{"t":4.025,"c":58},{"t":4.987,"c":73},{"t":6.025,"c":86},{"t":6.463,"c":93},{"t":7.813,"c":103},{"t":8.2,"c":109},{"t":8.838,"c":117},{"t":10.537,"c":130},{"t":10.8,"c":134},{"t":11.5,"c":146},{"t":11.975,"c":154},{"t":12.512,"c":163},{"t":13.275,"c":176},{"t":13.85,"c":184},{"t":14.412,"c":195},{"t":15.475,"c":208},{"t":16.113,"c":220},{"t":16.35,"c":224},{"t":17.825,"c":235},{"t":18.325,"c":241},{"t":18.637,"c":245},{"t":19.012,"c":249},{"t":19.637,"c":257},{"t":20.188,"c":263},{"t":20.738,"c":269},{"t":21.55,"c":283},{"t":22.675,"c":296},{"t":23.087,"c":304},{"t":23.762,"c":311},{"t":24.563,"c":320},{"t":25.188,"c":331},{"t":25.512,"c":335}]}