{"dur":24.25,"words":[{"t":0.1,"c":0},{"t":0.688,"c":7},{"t":1.137,"c":12},{"t":1.55,"c":16},{"t":1.913,"c":21},{"t":3.4,"c":29},{"t":3.688,"c":32},{"t":4.388,"c":41},{"t":4.575,"c":44},{"t":4.987,"c":49},{"t":5.5,"c":55},{"t":5.975,"c":62},{"t":6.713,"c":68},{"t":7.175,"c":74},{"t":7.912,"c":81},{"t":8.525,"c":91},{"t":9.125,"c":100},{"t":9.688,"c":107},{"t":11.05,"c":113},{"t":11.713,"c":120},{"t":12.1,"c":125},{"t":12.625,"c":133},{"t":13.137,"c":139},{"t":13.575,"c":144},{"t":13.863,"c":148},{"t":14.387,"c":154},{"t":15.75,"c":160},{"t":16.525,"c":168},{"t":16.913,"c":174},{"t":17.738,"c":184},{"t":17.962,"c":187},{"t":18.425,"c":193},{"t":19.012,"c":199},{"t":19.413,"c":203},{"t":19.688,"c":209},{"t":20.438,"c":215},{"t":21.262,"c":224},{"t":21.962,"c":231},{"t":22.375,"c":237},{"t":22.887,"c":244},{"t":23.45,"c":252},{"t":23.825,"c":257}]}