{"dur":30.225,"words":[{"t":0.1,"c":0},{"t":0.45,"c":4},{"t":0.975,"c":11},{"t":1.5,"c":19},{"t":2.063,"c":26},{"t":2.475,"c":33},{"t":2.938,"c":40},{"t":3.45,"c":46},{"t":4.625,"c":50},{"t":4.963,"c":53},{"t":5.438,"c":60},{"t":6.188,"c":68},{"t":6.6,"c":73},{"t":6.987,"c":79},{"t":8.488,"c":88},{"t":9.075,"c":95},{"t":9.775,"c":102},{"t":10.063,"c":105},{"t":10.325,"c":108},{"t":10.563,"c":111},{"t":11.15,"c":118},{"t":11.6,"c":125},{"t":12,"c":130},{"t":12.35,"c":135},{"t":13.2,"c":142},{"t":13.512,"c":145},{"t":14.387,"c":153},{"t":14.688,"c":156},{"t":15.075,"c":163},{"t":15.925,"c":171},{"t":16.3,"c":177},{"t":17.025,"c":186},{"t":17.325,"c":189},{"t":17.563,"c":192},{"t":18.9,"c":197},{"t":19.212,"c":200},{"t":19.725,"c":206},{"t":19.975,"c":209},{"t":20.238,"c":212},{"t":20.712,"c":219},{"t":21.025,"c":223},{"t":21.7,"c":228},{"t":22.262,"c":233},{"t":22.538,"c":236},{"t":22.825,"c":239},{"t":23.05,"c":242},{"t":24.575,"c":252},{"t":25.15,"c":259},{"t":25.575,"c":265},{"t":25.95,"c":270},{"t":26.2,"c":273},{"t":26.7,"c":281},{"t":27.012,"c":284},{"t":27.4,"c":288},{"t":27.975,"c":295},{"t":28.137,"c":298},{"t":28.563,"c":304},{"t":28.925,"c":309},{"t":29.35,"c":315},{"t":29.575,"c":318},{"t":29.938,"c":323}]}