{"dur":31.663,"words":[{"t":0.1,"c":0},{"t":0.55,"c":5},{"t":0.75,"c":8},{"t":1.137,"c":15},{"t":1.337,"c":18},{"t":1.65,"c":24},{"t":2.4,"c":31},{"t":2.875,"c":36},{"t":3.55,"c":41},{"t":4.612,"c":47},{"t":4.925,"c":50},{"t":5.213,"c":53},{"t":5.575,"c":58},{"t":6,"c":65},{"t":6.25,"c":70},{"t":6.412,"c":74},{"t":6.75,"c":80},{"t":7.088,"c":85},{"t":8.262,"c":90},{"t":8.738,"c":95},{"t":9.15,"c":102},{"t":9.55,"c":108},{"t":10.113,"c":116},{"t":10.563,"c":120},{"t":11.025,"c":127},{"t":11.188,"c":130},{"t":11.938,"c":135},{"t":12.188,"c":138},{"t":12.463,"c":141},{"t":12.988,"c":148},{"t":13.4,"c":152},{"t":13.762,"c":155},{"t":14.262,"c":162},{"t":14.813,"c":169},{"t":14.988,"c":172},{"t":16.35,"c":177},{"t":16.988,"c":182},{"t":17.288,"c":185},{"t":17.462,"c":188},{"t":17.813,"c":194},{"t":18,"c":197},{"t":18.413,"c":202},{"t":18.587,"c":206},{"t":18.913,"c":211},{"t":19.25,"c":216},{"t":19.788,"c":222},{"t":20.438,"c":229},{"t":21.212,"c":237},{"t":21.688,"c":243},{"t":22.425,"c":250},{"t":22.913,"c":256},{"t":23.212,"c":260},{"t":23.4,"c":263},{"t":24.075,"c":270},{"t":24.363,"c":273},{"t":24.975,"c":283},{"t":25.587,"c":288},{"t":26.05,"c":293},{"t":26.225,"c":296},{"t":26.75,"c":302},{"t":27,"c":305},{"t":27.325,"c":309},{"t":27.675,"c":313},{"t":28.012,"c":318},{"t":28.212,"c":321},{"t":28.775,"c":329},{"t":28.925,"c":332},{"t":29.2,"c":336},{"t":29.8,"c":340},{"t":30.238,"c":345},{"t":30.475,"c":348},{"t":30.8,"c":355},{"t":31.137,"c":359}]}