{"dur":26.025,"words":[{"t":0.1,"c":0},{"t":0.487,"c":7},{"t":1.038,"c":17},{"t":1.438,"c":24},{"t":1.925,"c":31},{"t":3.388,"c":39},{"t":3.95,"c":44},{"t":4.35,"c":48},{"t":5.175,"c":60},{"t":5.85,"c":72},{"t":6.737,"c":81},{"t":7.1,"c":86},{"t":7.75,"c":91},{"t":8.637,"c":99},{"t":10.137,"c":107},{"t":10.4,"c":112},{"t":11.488,"c":131},{"t":12.162,"c":137},{"t":13.137,"c":147},{"t":13.525,"c":152},{"t":14.287,"c":162},{"t":14.738,"c":167},{"t":16.025,"c":173},{"t":16.925,"c":184},{"t":17.837,"c":192},{"t":18.475,"c":202},{"t":19.938,"c":212},{"t":20.288,"c":216},{"t":20.85,"c":227},{"t":21.262,"c":234},{"t":21.625,"c":239},{"t":21.938,"c":244},{"t":22.762,"c":257},{"t":24,"c":277},{"t":25.2,"c":301},{"t":25.663,"c":308}]}