{"dur":29.313,"words":[{"t":0.1,"c":0},{"t":0.537,"c":4},{"t":1.313,"c":15},{"t":1.925,"c":23},{"t":3.4,"c":30},{"t":3.913,"c":36},{"t":4.213,"c":40},{"t":4.675,"c":47},{"t":5.112,"c":52},{"t":5.513,"c":58},{"t":6.175,"c":64},{"t":6.513,"c":71},{"t":6.75,"c":74},{"t":7.25,"c":80},{"t":7.575,"c":84},{"t":7.763,"c":87},{"t":8.162,"c":92},{"t":8.313,"c":95},{"t":9.875,"c":104},{"t":10.287,"c":111},{"t":10.688,"c":117},{"t":11.125,"c":124},{"t":11.588,"c":131},{"t":12.1,"c":139},{"t":12.787,"c":145},{"t":13.088,"c":148},{"t":13.438,"c":152},{"t":14.113,"c":161},{"t":14.375,"c":165},{"t":15.713,"c":171},{"t":16.712,"c":179},{"t":17.387,"c":187},{"t":18.3,"c":196},{"t":19.012,"c":204},{"t":20.563,"c":211},{"t":21.25,"c":218},{"t":21.65,"c":225},{"t":22.075,"c":233},{"t":22.9,"c":244},{"t":23.262,"c":248},{"t":23.738,"c":257},{"t":24.225,"c":264},{"t":24.85,"c":270},{"t":25.462,"c":277},{"t":25.788,"c":281},{"t":26.262,"c":288},{"t":27.637,"c":295},{"t":27.975,"c":299},{"t":28.938,"c":312}]}