{"dur":37.813,"words":[{"t":0.1,"c":0},{"t":0.613,"c":8},{"t":1.15,"c":15},{"t":2.188,"c":29},{"t":2.75,"c":37},{"t":3.45,"c":47},{"t":3.737,"c":51},{"t":4.025,"c":56},{"t":5.638,"c":67},{"t":6.662,"c":84},{"t":6.912,"c":88},{"t":7.563,"c":99},{"t":7.862,"c":106},{"t":8.887,"c":122},{"t":9.488,"c":130},{"t":10.688,"c":144},{"t":11.7,"c":153},{"t":12.7,"c":162},{"t":13.1,"c":167},{"t":13.95,"c":180},{"t":15.088,"c":196},{"t":16.087,"c":215},{"t":17.063,"c":228},{"t":18.05,"c":243},{"t":18.837,"c":251},{"t":20.35,"c":260},{"t":20.7,"c":267},{"t":21.413,"c":278},{"t":21.825,"c":286},{"t":22.313,"c":294},{"t":24.05,"c":307},{"t":24.337,"c":312},{"t":24.8,"c":320},{"t":25.25,"c":327},{"t":25.75,"c":332},{"t":26.95,"c":351},{"t":27.438,"c":361},{"t":27.813,"c":368},{"t":28.45,"c":378},{"t":28.813,"c":385},{"t":29.425,"c":396},{"t":29.775,"c":402},{"t":30.975,"c":421},{"t":31.712,"c":434},{"t":32.138,"c":443},{"t":32.45,"c":450},{"t":33.237,"c":458},{"t":35.2,"c":479},{"t":35.625,"c":487},{"t":36.35,"c":494},{"t":36.688,"c":499},{"t":37.025,"c":504}]}